Workbook

Sheet Overview_Dashboard
A1: Family Finance — Overview
A3: Summary KPIs
A4: Total Loan Payments | B4: =SUM(Loans!K5:K500)
A5: Total School Fees Paid | B5: =SUM(School_Fees!K5:K500)
A6: Total EMI Payments | B6: =SUM(EMIs!M5:M500)
A7: Other Expenses | B7: =SUM(Other_Expenses!F5:F500)
A8: Grand Total Outflow | B8: =B4+B5+B6+B7
A12: Category | B12: Amount
A13: Loans | B13: =SUM(Loans!K5:K500)
A14: School Fees | B14: =SUM(School_Fees!K5:K500)
A15: EMIs | B15: =SUM(EMIs!M5:M500)
A16: Other | B16: =SUM(Other_Expenses!F5:F500)
A22: Tip: Pin Overview_Dashboard as the first visible tab in Excel for a quick monthly review.

Sheet Loans_Dashboard
A1: Loans Dashboard
A3: Summary KPIs
A4: Total Paid (all time) | B4: =SUM(Loans!K5:K7)
A5: Total Interest Paid | B5: =SUM(Loans!M5:M7)
A6: Total Principal Paid | B6: =SUM(Loans!L5:L7)
A7: Pending / Overdue Count | B7: =COUNTIF(Loans!P5:P7,"Pending")+COUNTIF(Loans!P5:P7,"Overdue")
A9: Paid by Loan
A10: Loan_Name | B10: Total_Paid
A11: Home Loan | B11: =SUMIF(Loans!C5:C500,A11,Loans!K5:K500)
A12: Car Loan | B12: =SUMIF(Loans!C5:C500,A12,Loans!K5:K500)
A13: Personal Loan | B13: =SUMIF(Loans!C5:C500,A13,Loans!K5:K500)
A14: Education Loan | B14: =SUMIF(Loans!C5:C500,A14,Loans!K5:K500)
A17: Month | B17: Principal | C17: Interest
A18: Jan-25 | B18: 12000 | C18: 26500
A19: Feb-25 | B19: 12100 | C19: 26400

Sheet Loans
A1: Loans — Transaction Log
A2: Add one row per payment or due entry. Extend the table downward as needed.
A4: Entry_ID | B4: Entry_Date | C4: Loan_Name | D4: Lender | E4: Loan_Type | F4: Principal | G4: Interest_Rate | H4: Tenure_Months | I4: EMI_Amount | J4: Payment_Date | K4: Amount_Paid | L4: Principal_Paid | M4: Interest_Paid | N4: Outstanding_Balance | O4: Payment_Method | P4: Status | Q4: Notes
A5: 1 | B5: 45662 | C5: Home Loan | D5: HDFC | E5: Home Loan | F5: 4500000 | G5: 0.085 | H5: 240 | I5: 38500 | J5: 45662 | K5: 38500 | L5: 12000 | M5: 26500 | N5: 4388000 | O5: Auto Debit | P5: Paid | Q5: January EMI
A6: 2 | B6: 45693 | C6: Home Loan | D6: HDFC | E6: Home Loan | F6: 4500000 | G6: 0.085 | H6: 240 | I6: 38500 | J6: 45693 | K6: 38500 | L6: 12100 | M6: 26400 | N6: 4375900 | O6: Auto Debit | P6: Paid | Q6: February EMI
A7: 3 | B7: 45667 | C7: Car Loan | D7: SBI | E7: Car Loan | F7: 800000 | G7: 0.09 | H7: 60 | I7: 16600 | J7: 45667 | K7: 16600 | L7: 9800 | M7: 6800 | N7: 790200 | O7: Auto Debit | P7: Paid

Sheet School_Fees_Dashboard
A1: School Fees Dashboard
A3: Summary KPIs
A4: Total Fees Paid | B4: =SUM(School_Fees!K5:K7)
A5: Total Fees Due | B5: =SUM(School_Fees!H5:H7)
A6: Outstanding (Due - Paid) | B6: =SUM(School_Fees!H5:H7)-SUM(School_Fees!K5:K7)
A7: Pending Items | B7: =COUNTIF(School_Fees!M5:M7,"Pending")+COUNTIF(School_Fees!M5:M7,"Overdue")
A10: Child | B10: Paid
A11: Aarav | B11: =SUMIF(School_Fees!C5:C500,A11,School_Fees!K5:K500)
A12: Isha | B12: =SUMIF(School_Fees!C5:C500,A12,School_Fees!K5:K500)
A15: Fee_Type | B15: Amount
A16: Tuition | B16: =SUMIF(School_Fees!G5:G500,A16,School_Fees!K5:K500)
A17: Transport | B17: =SUMIF(School_Fees!G5:G500,A17,School_Fees!K5:K500)
A18: Books | B18: 0

Sheet School_Fees
A1: School Fees — Transaction Log
A2: Add one row per payment or due entry. Extend the table downward as needed.
A4: Entry_ID | B4: Entry_Date | C4: Child_Name | D4: School | E4: Academic_Year | F4: Term | G4: Fee_Type | H4: Amount_Due | I4: Due_Date | J4: Payment_Date | K4: Amount_Paid | L4: Payment_Method | M4: Status | N4: Notes
A5: 1 | B5: 45748 | C5: Aarav | D5: Delhi Public School | E5: 2025-26 | F5: Term 1 | G5: Tuition | H5: 45000 | I5: 45762 | J5: 45759 | K5: 45000 | L5: Bank Transfer | M5: Paid
A6: 2 | B6: 45748 | C6: Aarav | D6: Delhi Public School | E6: 2025-26 | F6: Term 1 | G6: Transport | H6: 12000 | I6: 45762 | J6: 45759 | K6: 12000 | L6: Bank Transfer | M6: Paid
A7: 3 | B7: 45748 | C7: Isha | D7: Ryan International | E7: 2025-26 | F7: Term 1 | G7: Tuition | H7: 38000 | I7: 45767 | K7: 0 | M7: Pending | N7: Due soon

Sheet EMIs_Dashboard
A1: EMIs Dashboard
A3: Summary KPIs
A4: Active EMIs | B4: =COUNTIF(EMIs!O5:O7,"Pending")+COUNTIF(EMIs!O5:O7,"Paid")
A5: Monthly EMI Outflow (active) | B5: =SUMIF(EMIs!O5:O500,"Pending",EMIs!G5:G500)
A6: Total Paid | B6: =SUM(EMIs!M5:M7)
A7: Completed EMIs | B7: =COUNTIF(EMIs!O5:O7,"Paid")
A10: Category | B10: EMI_Amount
A11: Appliance | B11: =SUMIF(EMIs!D5:D500,A11,EMIs!G5:G500)
A12: Electronics | B12: =SUMIF(EMIs!D5:D500,A12,EMIs!G5:G500)
A13: Furniture | B13: =SUMIF(EMIs!D5:D500,A13,EMIs!G5:G500)
A16: Month | B16: Paid
A17: Jan | B17: 4000
A18: Feb | B18: 4000
A19: Mar | B19: 4000

Sheet EMIs
A1: EMIs — Transaction Log
A2: Add one row per payment or due entry. Extend the table downward as needed.
A4: Entry_ID | B4: Entry_Date | C4: Item_Name | D4: Category | E4: Vendor_Lender | F4: Total_Price | G4: EMI_Amount | H4: Tenure_Months | I4: EMIs_Paid | J4: EMIs_Remaining | K4: Next_Due_Date | L4: Payment_Date | M4: Amount_Paid | N4: Payment_Method | O4: Status | P4: Notes
A5: 1 | B5: 45444 | C5: LG Refrigerator | D5: Appliance | E5: Bajaj Finserv | F5: 48000 | G5: 4000 | H5: 12 | I5: 8 | J5: 4 | K5: 45717 | L5: 45717 | M5: 4000 | N5: Auto Debit | O5: Paid
A6: 2 | B6: 45292 | C6: iPhone 15 | D6: Electronics | E6: HDFC Card EMI | F6: 90000 | G6: 7500 | H6: 12 | I6: 12 | J6: 0 | L6: 45627 | M6: 7500 | N6: Credit Card | O6: Paid | P6: Completed
A7: 3 | B7: 45536 | C7: Sofa Set | D7: Furniture | E7: Home Credit | F7: 36000 | G7: 3000 | H7: 12 | I7: 6 | J7: 6 | K7: 45748 | M7: 0 | O7: Pending

Sheet Other_Dashboard
A1: Other Expenses Dashboard
A3: Summary KPIs
A4: Total Spent | B4: =SUM(Other_Expenses!F5:F7)
A5: Recurring Expenses / month (est.) | B5: =SUMIFS(Other_Expenses!F5:F500,Other_Expenses!H5:H500,"Yes")
A6: Transactions Count | B6: =COUNTA(Other_Expenses!A5:A7)
A9: Category | B9: Spend
A10: Groceries | B10: =SUMIF(Other_Expenses!C5:C500,A10,Other_Expenses!F5:F500)
A11: Utilities | B11: =SUMIF(Other_Expenses!C5:C500,A11,Other_Expenses!F5:F500)
A12: Healthcare | B12: =SUMIF(Other_Expenses!C5:C500,A12,Other_Expenses!F5:F500)
A13: Travel | B13: =SUMIF(Other_Expenses!C5:C500,A13,Other_Expenses!F5:F500)

Sheet Other_Expenses
A1: Other Expenses — Transaction Log
A2: Add one row per payment or due entry. Extend the table downward as needed.
A4: Entry_ID | B4: Entry_Date | C4: Category | D4: Subcategory | E4: Description | F4: Amount | G4: Payment_Method | H4: Recurring | I4: Frequency | J4: Status | K4: Notes
A5: 1 | B5: 45660 | C5: Utilities | D5: Electricity | E5: BESCOM Jan | F5: 2800 | G5: UPI | H5: Yes | I5: Monthly | J5: Paid
A6: 2 | B6: 45665 | C6: Healthcare | D6: Doctor | E6: Annual checkup | F6: 1500 | G6: Cash | H6: No | J6: Paid
A7: 3 | B7: 45689 | C7: Groceries | D7: Supermarket | E7: Monthly stock | F7: 6200 | G7: UPI | H7: Yes | I7: Monthly | J7: Paid

Sheet Setup
A1: Personal Finance Tracker — Setup & Lists
A3: Use this sheet for dropdown values. Do not delete list headers.
A5: Payment_Methods | D5: Loan_Types | G5: Fee_Types | J5: EMI_Categories | M5: Expense_Categories | P5: Status_Values
A6: Cash | D6: Home Loan | G6: Tuition | J6: Appliance | M6: Groceries | P6: Paid
A7: UPI | D7: Personal Loan | G7: Transport | J7: Electronics | M7: Utilities | P7: Pending
A8: Bank Transfer | D8: Car Loan | G8: Books | J8: Furniture | M8: Healthcare | P8: Overdue
A9: Credit Card | D9: Education Loan | G9: Uniform | J9: Vehicle | M9: Travel | P9: Partial
A10: Debit Card | D10: Gold Loan | G10: Activity | J10: Insurance | M10: Entertainment | P10: Skipped
A11: Auto Debit | D11: Other | G11: Exam | J11: Subscription | M11: Maintenance
G12: Other | J12: Other | M12: Other
A14: Recommended workflow
A15: 1. Enter transactions only in the data sheets (Loans, School_Fees, EMIs, Other_Expenses).
A16: 2. Use one row per payment or due entry — avoid mixing summary and detail on the same row.
A17: 3. Open each *_Dashboard sheet for charts; they refresh when you add rows to the matching data table.
A18: 4. Keep dates in a single column (Entry_Date) and amounts in numeric columns only.
A19: 5. Use Status + Due_Date to track pending items across all sheets.
